Metadata-Version: 1.2
Name: approxidate
Version: 1.0.4
Summary: a quick way to get a unix timestamp from arbitrary date formats
Home-page: https://github.com/thatguystone/approxidate
Author: Andrew Stone
Author-email: a@stne.dev
License: GPL v2
Project-URL: Source, https://github.com/thatguystone/approxidate
Project-URL: Tracker, https://github.com/thatguystone/approxidate/issues
Platform: UNKNOWN
